ragged-stubs/__init__.pyi
ragged-stubs/_helper_functions.pyi
ragged-stubs/_import.pyi
ragged-stubs/_spec_array_object.pyi
ragged-stubs/_spec_constants.pyi
ragged-stubs/_spec_creation_functions.pyi
ragged-stubs/_spec_data_type_functions.pyi
ragged-stubs/_spec_elementwise_functions.pyi
ragged-stubs/_spec_indexing_functions.pyi
ragged-stubs/_spec_linear_algebra_functions.pyi
ragged-stubs/_spec_manipulation_functions.pyi
ragged-stubs/_spec_searching_functions.pyi
ragged-stubs/_spec_set_functions.pyi
ragged-stubs/_spec_sorting_functions.pyi
ragged-stubs/_spec_statistical_functions.pyi
ragged-stubs/_spec_utility_functions.pyi
ragged-stubs/_typing.pyi
ragged-stubs/_version.pyi
ragged-stubs/io/__init__.pyi
ragged-stubs/io/cf.pyi
ragged_stubs-0.2.0a6.dist-info/WHEEL
ragged_stubs-0.2.0a6.dist-info/METADATA
ragged_stubs-0.2.0a6.dist-info/RECORD
